{
  "db_name": "PostgreSQL",
  "query": "\nSELECT\n    allowance,\n    allowance_locked,\n    pending_transaction_hash\nFROM\n    account\nWHERE\n    account_id = $1\n",
  "describe": {
    "columns": [
      {
        "ordinal": 0,
        "name": "allowance",
        "type_info": "Numeric"
      },
      {
        "ordinal": 1,
        "name": "allowance_locked",
        "type_info": "Numeric"
      },
      {
        "ordinal": 2,
        "name": "pending_transaction_hash",
        "type_info": "Varchar"
      }
    ],
    "parameters": {
      "Left": [
        "Text"
      ]
    },
    "nullable": [
      false,
      false,
      true
    ]
  },
  "hash": "184ff85f7ca14b5f4ca1edbb8f3aa6b33041d99473a86b4a3d0ea079b2737f17"
}
